Metadata-Version: 2.1
Name: pythonvalueobject
Version: 1.0.0
Summary: Python value object implementation
Home-page: https://github.com/virtualitems
Author: github@virtualitems
Author-email: virtualitemsuniverse@gmail.com
License: MIT
Keywords: value,object
Platform: UNKNOWN
Classifier: Intended Audience :: Developers
Classifier: Programming Language :: Python :: 3
License-File: LICENSE
